runrate_properties_pkg/__init__.py
runrate_properties_pkg/runrate_properties.py
RunRate-0.0.5.dist-info/LICENCE.txt
RunRate-0.0.5.dist-info/METADATA
RunRate-0.0.5.dist-info/WHEEL
RunRate-0.0.5.dist-info/top_level.txt
RunRate-0.0.5.dist-info/RECORD
